{
  "version": 1,
  "mrn": ,
  "session": ,
  "signed": false,
  "signer": "", "signtime" : "",
  "template": "dx_lumbar_spine",
  "history": {
    "patient_age": "",
    "patient_history": ""
  },
  "title": "XRAY LUMBAR SPINE",
  "technique": {
    "description": "2 views of the lumbar spine acquired.",
    "comparison": ""
  },
  "fseq": [
    "findings:FINDINGS:BOX"
  ],
  "findings": {
    "findings": "Normal alignment. Normal vertebral body height. No acute fracture. Disc spaces are normal."
  },
  "impression": "Normal lumbar spine."
}
